trustregion/__init__.py
trustregion/_trs.cpython-310-x86_64-linux-gnu.so
trustregion/interface.py
trustregion/trsapp.f90
trustregion/trsbox.f90
trustregion/trslin.f90
trustregion/tests/test_interface.py
trustregion-1.2.2.dist-info/METADATA
trustregion-1.2.2.dist-info/WHEEL
trustregion-1.2.2.dist-info/RECORD
trustregion-1.2.2.dist-info/licenses/LICENSE
