Metadata-Version: 2.2
Name: trustregion
Version: 1.2.2
Summary: Trust-region subproblem solvers for nonlinear/nonconvex optimization
Keywords: mathematics,optimization
Author-Email: Lindon Roberts <lindon.roberts@sydney.edu.au>
Maintainer-Email: Lindon Roberts <lindon.roberts@sydney.edu.au>
License: GPL-3.0-or-later
Classifier: Development Status :: 5 - Production/Stable
Classifier: Environment :: Console
Classifier: Framework :: IPython
Classifier: Framework :: Jupyter
Classifier: Intended Audience :: Science/Research
Classifier: License :: OSI Approved :: GNU General Public License v3 or later (GPLv3+)
Classifier: Operating System :: MacOS
Classifier: Operating System :: Microsoft :: Windows
Classifier: Operating System :: Unix
Classifier: Programming Language :: Python
Classifier: Programming Language :: Python :: 3
Classifier: Programming Language :: Python :: 3.8
Classifier: Programming Language :: Python :: 3.9
Classifier: Programming Language :: Python :: 3.10
Classifier: Programming Language :: Python :: 3.11
Classifier: Programming Language :: Python :: 3.12
Classifier: Topic :: Scientific/Engineering
Classifier: Topic :: Scientific/Engineering :: Mathematics
Project-URL: Homepage, https://github.com/lindonroberts/trust-region
Project-URL: Download, https://github.com/lindonroberts/trust-region/releases/
Project-URL: Bug Tracker, https://github.com/lindonroberts/trust-region/issues/
Project-URL: Documentation, https://github.com/lindonroberts/trust-region
Project-URL: Source Code, https://github.com/lindonroberts/trust-region
Requires-Python: >=3.8
Requires-Dist: numpy
Provides-Extra: dev
Requires-Dist: pytest; extra == "dev"
